{"code":"102571","kind":"CRS-PROJCRS","name":"WGS 1984 UTM Zone 21N using TM Complex","wkt":"PROJCS[\"WGS_1984_Complex_UTM_Zone_21N\",GEOGCS[\"WGS 84\",DATUM[\"WGS_1984\",SPHEROID[\"WGS 84\",6378137,298.257223563,AUTHORITY[\"EPSG\",\"7030\"]],AUTHORITY[\"EPSG\",\"6326\"]],PRIMEM[\"Greenwich\",0],UNIT[\"Degree\",0.0174532925199433]],PROJECTION[\"Transverse_Mercator\"],PARAMETER[\"latitude_of_origin\",0],PARAMETER[\"central_meridian\",-57],PARAMETER[\"scale_factor\",0.9996],PARAMETER[\"false_easting\",500000],PARAMETER[\"false_northing\",0],UNIT[\"metre\",1,AUTHORITY[\"EPSG\",\"9001\"]],AXIS[\"Easting\",EAST],AXIS[\"Northing\",NORTH],AUTHORITY[\"ESRI\",\"102571\"]]","proj4":"+proj=utm +zone=21 +datum=WGS84 +units=m +no_defs +type=crs","bbox":[84,-60,0,-54],"unit":null,"area":"World - N hemisphere - 60~W to 54~W","accuracy":null}