{"code":"2313","kind":"CRS-PROJCRS","name":"Kousseri / UTM zone 33N","wkt":"PROJCS[\"Kousseri / UTM zone 33N\",GEOGCS[\"Kousseri\",DATUM[\"Kousseri\",SPHEROID[\"Clarke 1880 (RGS)\",6378249.145,293.465],TOWGS84[-104.4,-136.6,201.2,0,0,0,0]],PRIMEM[\"Greenwich\",0,AUTHORITY[\"EPSG\",\"8901\"]],UNIT[\"degree\",0.0174532925199433,AUTHORITY[\"EPSG\",\"9122\"]],AUTHORITY[\"EPSG\",\"4198\"]],PROJECTION[\"Transverse_Mercator\"],PARAMETER[\"latitude_of_origin\",0],PARAMETER[\"central_meridian\",15],PARAMETER[\"scale_factor\",0.9996],PARAMETER[\"false_easting\",500000],PARAMETER[\"false_northing\",0],UNIT[\"metre\",1,AUTHORITY[\"EPSG\",\"9001\"]],AXIS[\"Easting\",EAST],AXIS[\"Northing\",NORTH],AUTHORITY[\"EPSG\",\"2313\"]]","proj4":"+proj=utm +zone=33 +a=6378249.145 +rf=293.465 +towgs84=-104.4,-136.6,201.2,0,0,0,0 +units=m +no_defs +type=crs","bbox":[12.77,14.17,11.7,15.09],"unit":"metre","area":"Cameroon - N'Djamena area.","accuracy":5}