{"code":"26781","kind":"CRS-PROJCRS","name":"NAD27 / Louisiana North","wkt":"PROJCS[\"NAD27 / Louisiana North\",GEOGCS[\"NAD27\",DATUM[\"North_American_Datum_1927\",SPHEROID[\"Clarke 1866\",6378206.4,294.978698213898],EXTENSION[\"PROJ4_GRIDS\",\"NTv2_0.gsb\"]],PRIMEM[\"Greenwich\",0,AUTHORITY[\"EPSG\",\"8901\"]],UNIT[\"degree\",0.0174532925199433,AUTHORITY[\"EPSG\",\"9122\"]],AUTHORITY[\"EPSG\",\"4267\"]],PROJECTION[\"Lambert_Conformal_Conic_2SP\"],PARAMETER[\"latitude_of_origin\",30.6666666666667],PARAMETER[\"central_meridian\",-92.5],PARAMETER[\"standard_parallel_1\",31.1666666666667],PARAMETER[\"standard_parallel_2\",32.6666666666667],PARAMETER[\"false_easting\",2000000],PARAMETER[\"false_northing\",0],UNIT[\"US survey foot\",0.304800609601219],AXIS[\"Easting\",EAST],AXIS[\"Northing\",NORTH],AUTHORITY[\"EPSG\",\"26781\"]]","proj4":"+proj=lcc +lat_0=30.6666666666667 +lon_0=-92.5 +lat_1=31.1666666666667 +lat_2=32.6666666666667 +x_0=609601.219202438 +y_0=0 +ellps=clrk66 +nadgrids=NTv2_0.gsb +units=us-ft +no_defs +type=crs","bbox":[33.03,-94.05,30.85,-90.86],"unit":"US survey foot","area":"United States (USA) - Louisiana - counties of Avoyelles; Bienville; Bossier; Caddo; Caldwell; Catahoula; Claiborne; Concordia; De Soto; East Carroll; Franklin; Grant; Jackson; La Salle; Lincoln; Madison; Morehouse; Natchitoches; Ouachita; Rapides; Red River; Richland; Sabine; Tensas; Union; Vernon; Webster; West Carroll; Winn.","accuracy":2}