{"code":"3663","kind":"CRS-PROJCRS","name":"NAD83(NSRS2007) / Texas Central","wkt":"PROJCS[\"NAD83(NSRS2007) / Texas Central\",GEOGCS[\"NAD83(NSRS2007)\",DATUM[\"NAD83_National_Spatial_Reference_System_2007\",SPHEROID[\"GRS 1980\",6378137,298.257222101],TOWGS84[0,0,0,0,0,0,0]],PRIMEM[\"Greenwich\",0,AUTHORITY[\"EPSG\",\"8901\"]],UNIT[\"degree\",0.0174532925199433,AUTHORITY[\"EPSG\",\"9122\"]],AUTHORITY[\"EPSG\",\"4759\"]],PROJECTION[\"Lambert_Conformal_Conic_2SP\"],PARAMETER[\"latitude_of_origin\",29.6666666666667],PARAMETER[\"central_meridian\",-100.333333333333],PARAMETER[\"standard_parallel_1\",31.8833333333333],PARAMETER[\"standard_parallel_2\",30.1166666666667],PARAMETER[\"false_easting\",700000],PARAMETER[\"false_northing\",3000000],UNIT[\"metre\",1,AUTHORITY[\"EPSG\",\"9001\"]],AXIS[\"Easting\",EAST],AXIS[\"Northing\",NORTH],AUTHORITY[\"EPSG\",\"3663\"]]","proj4":"+proj=lcc +lat_0=29.6666666666667 +lon_0=-100.333333333333 +lat_1=31.8833333333333 +lat_2=30.1166666666667 +x_0=700000 +y_0=3000000 +ellps=GRS80 +towgs84=0,0,0,0,0,0,0 +units=m +no_defs +type=crs","bbox":[32.27,-106.66,29.78,-93.5],"unit":"metre","area":"United States (USA) - Texas - counties of Anderson; Angelina; Bastrop; Bell; Blanco; Bosque; Brazos; Brown; Burleson; Burnet; Cherokee; Coke; Coleman; Comanche; Concho; Coryell; Crane; Crockett; Culberson; Ector; El Paso; Falls; Freestone; Gillespie; Glasscock; Grimes; Hamilton; Hardin; Houston; Hudspeth; Irion; Jasper; Jeff Davis; Kimble; Lampasas; Lee; Leon; Liberty; Limestone; Llano; Loving; Madison; Mason; McCulloch; McLennan; Menard; Midland; Milam; Mills; Montgomery; Nacogdoches; Newton; Orange; Pecos; Polk; Reagan; Reeves; Robertson; Runnels; Sabine; San Augustine; San Jacinto; San Saba; Schleicher; Shelby; Sterling; Sutton; Tom Green; Travis; Trinity; Tyler; Upton; Walker; Ward; Washington; Williamson; Winkler.","accuracy":2}