{"code":"6881","kind":"CRS-GEOGCRS","name":"Aden 1925","wkt":"GEOGCS[\"Aden 1925\",DATUM[\"Aden_1925\",SPHEROID[\"Clarke 1880 (RGS)\",6378249.145,293.465],TOWGS84[-24,-203,268,0,0,0,0]],PRIMEM[\"Greenwich\",0,AUTHORITY[\"EPSG\",\"8901\"]],UNIT[\"degree\",0.0174532925199433,AUTHORITY[\"EPSG\",\"9122\"]],AUTHORITY[\"EPSG\",\"6881\"]]","proj4":"+proj=longlat +a=6378249.145 +rf=293.465 +towgs84=-24,-203,268,0,0,0,0 +no_defs +type=crs","bbox":[19,43.37,12.54,53.14],"unit":"degree (supplier to define representation)","area":"Yemen - South Yemen onshore mainland.","accuracy":999}