{"code":"9391","kind":"CRS-PROJCRS","name":"BGS2005 / UTM zone 35N","wkt":"PROJCS[\"BGS2005 / UTM zone 35N\",GEOGCS[\"BGS2005\",DATUM[\"Bulgaria_Geodetic_System_2005\",SPHEROID[\"GRS 1980\",6378137,298.257222101],TOWGS84[0,0,0,0,0,0,0]],PRIMEM[\"Greenwich\",0,AUTHORITY[\"EPSG\",\"8901\"]],UNIT[\"degree\",0.0174532925199433,AUTHORITY[\"EPSG\",\"9122\"]],AUTHORITY[\"EPSG\",\"7798\"]],PROJECTION[\"Transverse_Mercator\"],PARAMETER[\"latitude_of_origin\",0],PARAMETER[\"central_meridian\",27],PARAMETER[\"scale_factor\",0.9996],PARAMETER[\"false_easting\",500000],PARAMETER[\"false_northing\",0],UNIT[\"metre\",1,AUTHORITY[\"EPSG\",\"9001\"]],AXIS[\"Easting\",EAST],AXIS[\"Northing\",NORTH],AUTHORITY[\"EPSG\",\"9391\"]]","proj4":"+proj=utm +zone=35 +ellps=GRS80 +towgs84=0,0,0,0,0,0,0 +units=m +no_defs +type=crs","bbox":[44.15,24,41.24,30.01],"unit":"metre","area":"Bulgaria - onshore east of 24°E, offshore west of 30°E.","accuracy":1}